ci/transparency/ptag/spec/__init__.py
ci/transparency/ptag/spec/__pycache__/__init__.cpython-312.pyc
ci/transparency/ptag/spec/schemas/ptag.schema.json
ci/transparency/ptag/spec/schemas/ptag_api.openapi.yaml
ci/transparency/ptag/spec/schemas/ptag_series.schema.json
civic_transparency_ptag_spec-0.2.5.data/data/share/civic-transparency-ptag-spec/CITATION.cff
civic_transparency_ptag_spec-0.2.5.data/data/share/civic-transparency-ptag-spec/LICENSE
civic_transparency_ptag_spec-0.2.5.data/data/share/civic-transparency-ptag-spec/README.md
civic_transparency_ptag_spec-0.2.5.dist-info/licenses/LICENSE
civic_transparency_ptag_spec-0.2.5.dist-info/METADATA
civic_transparency_ptag_spec-0.2.5.dist-info/WHEEL
civic_transparency_ptag_spec-0.2.5.dist-info/top_level.txt
civic_transparency_ptag_spec-0.2.5.dist-info/RECORD
